provider_google_genai.py
opsmate_provider_google_genai-0.1.1a0.dist-info/METADATA
opsmate_provider_google_genai-0.1.1a0.dist-info/WHEEL
opsmate_provider_google_genai-0.1.1a0.dist-info/entry_points.txt
opsmate_provider_google_genai-0.1.1a0.dist-info/licenses/LICENSE
opsmate_provider_google_genai-0.1.1a0.dist-info/RECORD
