Metadata-Version: 2.4
Name: opsmate-provider-google-genai
Version: 0.1.1a0
Summary: Google GenAI provider for opsmate
Author-email: Jingkai He <jingkai@hey.com>
License: MIT License
License-File: LICENSE
Requires-Python: <4.0,>=3.10
Requires-Dist: google-genai>=1.5.0
Requires-Dist: jsonref<2.0.0,>=1.1.0
Requires-Dist: opsmate
